{
  "gitSyncId": "68b93a5bde8045780e9358a0_acc4d987-41dd-49e1-b157-78a3236a089b",
  "id": "Home page_JSObject1.next_service",
  "pluginId": "js-plugin",
  "pluginType": "JS",
  "unpublishedAction": {
    "actionConfiguration": {
      "encodeParamsToggle": true,
      "isAsync": false,
      "jsArguments": [],
      "paginationType": "NONE",
      "timeoutInMillisecond": 10000
    },
    "collectionId": "Home page_JSObject1",
    "confirmBeforeExecute": false,
    "datasource": {
      "isAutoGenerated": false,
      "name": "UNUSED_DATASOURCE",
      "pluginId": "js-plugin"
    },
    "dynamicBindingPathList": [
      {
        "key": "body"
      }
    ],
    "fullyQualifiedName": "JSObject1.next_service",
    "name": "next_service",
    "pageId": "Home page",
    "runBehaviour": "MANUAL",
    "userSetOnLoad": false
  }
}